bqSQLrunner/__init__.py
bqSQLrunner/bqSQLrunner.py
bqSQLrunner/cli.py
bqSQLrunner/mainBqSQLrunner.py
bqSQLrunner-1.0.12.dist-info/METADATA
bqSQLrunner-1.0.12.dist-info/WHEEL
bqSQLrunner-1.0.12.dist-info/top_level.txt
bqSQLrunner-1.0.12.dist-info/RECORD
