Metadata-Version: 2.1
Name: bqSQLrunner
Version: 1.0.12
Summary: A Python framework for running SQL steps on BigQuery, with support for variables and dependencies. Developed by Martin Birkholz and maintained by Iulian.
Author: Martin Birkholz / Iulian
Author-email: iulian.glavan@metro.digital
Requires-Python: >=3.7
Requires-Dist: google-cloud-bigquery>=2.0.0
